{"account": "Beautyandyouth_official", "tags": ["xmas", "bywomens16", "beautyandyouth", "by_holidaysgift2016", "gift", "byfw16"], "face_result": 0, "caption_text": "\uff1cBEAUTY&YOUTH\uff1e 2WAY GLOVES \u00a55,000(+tax) FROM THE FW 2016WOMEN'S COLLECTION\n#BEAUTYANDYOUTH #BY_HOLIDAYSGIFT2016 #xmas #gift  #BYWOMENS16 #BYFW16", "user_in_photo": false, "longitude": "", "created_time": "1481187249", "link": "https://www.instagram.com/p/BNwAtrkgB-k/", "latitude": "", "comments_count": 0, "personality": {"cute": "1.30457e-11", "natural": "1.75626e-09", "wild": "1.72063e-06", "elegant": "2.61563e-07", "steady": "0.841962", "sophisticated": "0.00457128", "gentle": "1.03062e-10", "lively": "6.26466e-11", "pure": "3.20158e-12", "gorgeous": "6.71864e-11", "fun": "3.00411e-11", "smart": "0.153465"}, "id": "1400622623271952292_1688403291", "types": "brand", "likes_count": 506}