{"account": "Beautyandyouth_official", "tags": ["byss17", "unitedarrows", "bymens17", "h_beautyandyouth", "beautyandyouth", "headofstate"], "face_result": 0, "caption_text": "\uff1cHEAD OF STATE\uff1eFROM THE SS 2017 MEN'S COLLECTION\nTEE \u00a54,800(\uff0btax) L/TEE\u00a55,800(\uff0btax)SWEAT\u00a56,800(\uff0btax)JACKET\uffe543,000(\uff0btax)PANTS \uffe532,000(\uff0btax)SHORTS\uffe526,000(\uff0btax)\n18\u6b73\u306e\u30c7\u30b6\u30a4\u30ca\u30fc\u306b\u3088\u308b\u3001NY\u306e\u65b0\u9032\u30d6\u30e9\u30f3\u30c9\u304c\u5165\u8377\u3057\u307e\u3057\u305f\u3002\u82e5\u3055\u306e\u3042\u308b\u552f\u4e00\u7121\u4e8c\u306e\u30c7\u30b6\u30a4\u30f3\u306b\u6ce8\u76ee\u3002\u56fd\u5185\u8ca9\u8def\u306fB&Y \u9650\u5b9a\u3002#HEADOFSTATE#BEAUTYANDYOUTH #H_beautyandyouth#UnitedArrows#BYMENS17 #BYSS17 @headofstate_", "user_in_photo": false, "longitude": "", "created_time": "1484734957", "link": "https://www.instagram.com/p/BPZvbcOgACy/", "latitude": "", "comments_count": 2, "personality": {"cute": "0.0116402", "natural": "6.81845e-09", "wild": "1.28097e-06", "elegant": "0.96875", "steady": "4.24172e-09", "sophisticated": "0.000110728", "gentle": "1.52442e-08", "lively": "2.01669e-07", "pure": "8.14725e-06", "gorgeous": "0.000730415", "fun": "0.0187582", "smart": "6.22457e-07"}, "id": "1430382950586777778_1688403291", "types": "brand", "likes_count": 1249}