{"account": "Beautyandyouth_official", "tags": ["byss17", "beautyandyouth", "bywomens17", "suicoke", "by\u5225\u6ce8"], "face_result": 0, "caption_text": "\uff1cSUICOKE\uff1e SLIDER SANDAL \uffe58,000\uff08\uff0btax\uff09\nFROM THE SS 2017 WOMENS COLLECTION\n\uff1cSUICOKE\uff1e\u3088\u308a\u30b9\u30e9\u30a4\u30c0\u30fc\u578b\u30b5\u30f3\u30c0\u30eb\u306e\u65b0\u4f5c\u304c\u767b\u5834\u81f4\u3057\u307e\u3057\u305f\u3002\n\u30d9\u30eb\u30c8\u3067\u8abf\u6574\u53ef\u80fd\u306a\u30a2\u30c3\u30d1\u30fc\u3068\u8db3\u306b\u30d5\u30a3\u30c3\u30c8\u3059\u308b\u30af\u30c3\u30b7\u30e7\u30f3\u6027\u306e\u9ad8\u3044\u30bd\u30fc\u30eb\u3092\u4f7f\u7528\u3057\u3066\u3044\u308b\u306e\u3067\u5feb\u9069\u306a\u5c65\u304d\u5fc3\u5730\u306b\u3002\n\u30aa\u30fc\u30eb\u30db\u30ef\u30a4\u30c8\u306f\u30a4\u30f3\u30e9\u30a4\u30f3\u306b\u306f\u306a\u3044B&Y\u3060\u3051\u306e\u5225\u6ce8\u30e2\u30c7\u30eb\u3067\u3059\u3002\n#SUICOKE  #BEAUTYANDYOUTH #BYWOMENS17 #BYSS17 #BY\u5225\u6ce8", "user_in_photo": false, "longitude": "", "created_time": "1493099371", "link": "https://www.instagram.com/p/BTTBSJOl5Bv/", "latitude": "", "comments_count": 2, "personality": {"cute": "0.00483022", "natural": "0.00642085", "wild": "5.41542e-09", "elegant": "0.973375", "steady": "2.29687e-07", "sophisticated": "0.00515448", "gentle": "3.90992e-06", "lively": "3.28209e-11", "pure": "0.0101389", "gorgeous": "1.08757e-05", "fun": "9.77148e-09", "smart": "6.60157e-05"}, "id": "1500548745750089839_1688403291", "types": "brand", "likes_count": 1434}