{"account": "Beautyandyouth_official", "tags": ["beautyandyouth", "bymens17", "byss17", "sale"], "face_result": 0, "caption_text": "\u3010INFORMATION\u3011\n\u307f\u306a\u3055\u307e\u306e\u65e5\u9803\u306e\u3054\u611b\u9867\u306b\u611f\u8b1d\u3057\u30017\u670828\u65e5(\u91d1)\u3088\u308aFINAL SALE\u3092\u958b\u50ac\u3044\u305f\u3057\u307e\u3059\u3002\u2028\u30bb\u30fc\u30eb\u5bfe\u8c61\u5546\u54c1\u304c\u6700\u7d42\u4fa1\u683c\u3068\u306a\u308a\u3055\u3089\u306b\u304a\u6c42\u3081\u3084\u3059\u304f\u306a\u308a\u307e\u3059\u3002\u3053\u306e\u6a5f\u4f1a\u3092\u3069\u3046\u305e\u304a\u898b\u9003\u3057\u306a\u304f\u3002 #BEAUTYANDYOUTH  #BYMENS17 #BYSS17 #SALE", "user_in_photo": false, "longitude": "", "created_time": "1501064175", "link": "https://www.instagram.com/p/BXAY8SEF3Dp/", "latitude": "", "comments_count": 0, "personality": {"cute": "0.00832231", "natural": "3.84938e-09", "wild": "2.40646e-06", "elegant": "5.94328e-06", "steady": "2.39705e-09", "sophisticated": "4.62267e-09", "gentle": "4.85042e-11", "lively": "0.0005571", "pure": "2.40775e-07", "gorgeous": "2.17829e-07", "fun": "0.991112", "smart": "1.96494e-08"}, "id": "1567362366005801193_1688403291", "types": "brand", "likes_count": 530}