{"account": "Beautyandyouth_official", "tags": ["beautyandyouth", "byfw17", "nike", "nikesportswear", "bymens"], "face_result": 0, "caption_text": "\u3010PICK UP ITEM\u3011\n\u6d17\u7df4\u3055\u308c\u305f\u30c7\u30b6\u30a4\u30f3\u3068\u5feb\u9069\u306a\u7740\u7528\u611f\u30ca\u30a4\u30ad \u30a8\u30a2 \u30de\u30c3\u30af\u30b9 97 \u30a6\u30eb\u30c8\u30e9 '17 \u30e1\u30f3\u30ba\u30b7\u30e5\u30fc\u30ba\u306f\u3001\u9ad8\u901f\u65b0\u5e79\u7dda\u306e\u6d17\u7df4\u3055\u308c\u305f\u6a5f\u80fd\u6027\u3068\u5916\u89b3\u3092\u30a4\u30e1\u30fc\u30b8\u3057\u305f\u4e00\u8db3\u3002\u8efd\u91cf\u69cb\u9020\u3068\u9ad8\u53cd\u767a\u306e\u30af\u30c3\u30b7\u30e7\u30cb\u30f3\u30b0\u3067\u3001\u3044\u3064\u3067\u3082\u5feb\u9069\u306a\u5c65\u304d\u5fc3\u5730\u3092\u63d0\u4f9b\u3057\u307e\u3059\u3002\n\uff1cNIKE SPORTS WEAR\uff1e\n\u767a\u58f2\u65e5:8\u670817\u65e5\uff08\u6728\uff09\n\u00a517,000(+tax)\n\u203b\u8a73\u3057\u304f\u306f\u30bb\u30fc\u30eb\u30b9\u30d1\u30fc\u30bd\u30f3\u306b\u304a\u5c0b\u306d\u4e0b\u3055\u3044\u3002\n#NIKE #nikesportswear #BEAUTYANDYOUTH #BYMENS #BYFW17", "user_in_photo": false, "longitude": "", "created_time": "1502963365", "link": "https://www.instagram.com/p/BX4_XAklNaN/", "latitude": "", "comments_count": 0, "personality": {"cute": "1.35486e-10", "natural": "5.82781e-11", "wild": "6.00334e-10", "elegant": "0.999997", "steady": "1.13216e-11", "sophisticated": "9.63696e-08", "gentle": "1.79827e-06", "lively": "6.38766e-07", "pure": "3.44653e-08", "gorgeous": "2.47021e-07", "fun": "7.81594e-10", "smart": "8.52243e-09"}, "id": "1583293927112627853_1688403291", "types": "brand", "likes_count": 872}