{"account": "Beautyandyouth_official", "tags": ["beautyandyouth", "byfw17", "timberland", "oceansoffthecity", "bymens17"], "face_result": 0, "caption_text": "\u3010COMING SOON\u3011\n\uff1cnonnative\uff1e\u00d7\uff1cTimberland\uff1e\nSUPER 6 INCH BOOTS GORE-TEX\u00ae\n\u00a532,000\uff08+tax )\n\u767a\u58f2\u65e5\uff1a9\u67082\u65e5\uff08\u571f\uff09\n@oceans_magazine #oceansoffthecity\n@that_nonnative\n#Timberland\n#BEAUTYANDYOUTH  #BYMENS17#BYFW17", "user_in_photo": false, "longitude": "", "created_time": "1504006446", "link": "https://www.instagram.com/p/BYYE4LcHEp7/", "latitude": "", "comments_count": 0, "personality": {"cute": "0.000173898", "natural": "2.33763e-06", "wild": "1.84512e-05", "elegant": "0.00116263", "steady": "0.000152292", "sophisticated": "0.0113645", "gentle": "0.0048352", "lively": "0.000278267", "pure": "2.06965e-05", "gorgeous": "0.000924044", "fun": "0.00696312", "smart": "0.974105"}, "id": "1592043921034988155_1688403291", "types": "brand", "likes_count": 788}