{"account": "Beautyandyouth_official", "tags": ["\u30d5\u30a7\u30a4\u30af\u30d5\u30a1\u30fc", "\u30b7\u30e7\u30fc\u30c8\u30b3\u30fc\u30c8", "byfw17", "beautyandyouth", "\u30d5\u30a7\u30a4\u30af\u30d5\u30a1\u30fc\u30b3\u30fc\u30c8", "bywomens17"], "face_result": 1, "caption_text": "\u3010NEW ARRIVAL\u3011\n\u6bdb\u8db3\u306e\u9577\u3044\u30d5\u30a7\u30a4\u30af\u30d5\u30a1\u30fc\u306e\u30b7\u30e7\u30fc\u30c8\u30b3\u30fc\u30c8\u3002\n\u307b\u3069\u3088\u3044\u8cea\u611f\u3068\u3059\u3063\u304d\u308a\u3068\u3057\u305f\u7740\u4e08\u304c\u3001\u30b9\u30bf\u30a4\u30ea\u30f3\u30b0\u3092\u30b0\u30c3\u3068\u3057\u3081\u307e\u3059\u3002\n\u30d6\u30e9\u30a6\u30f31\u8272\u306e\u307f\u306e\u5c55\u958b\u3067\u3059\u3002\n\uff1cBEAUTY&YOUTH\uff1e FAKE FUR SHORT COAT\uffe525,000\uff08\uff0btax\uff09\n#BEAUTYANDYOUTH #BYWOMENS17 #BYFW17 #\u30d5\u30a7\u30a4\u30af\u30d5\u30a1\u30fc #\u30d5\u30a7\u30a4\u30af\u30d5\u30a1\u30fc\u30b3\u30fc\u30c8 #\u30b7\u30e7\u30fc\u30c8\u30b3\u30fc\u30c8", "user_in_photo": true, "longitude": "", "created_time": "1508298760", "link": "https://www.instagram.com/p/BaX_0V3n5hf/", "latitude": "", "comments_count": 0, "personality": {"cute": "0.000592996", "natural": "0.0181672", "wild": "9.85796e-06", "elegant": "0.0681494", "steady": "0.000565344", "sophisticated": "0.114813", "gentle": "0.156151", "lively": "0.000211642", "pure": "0.000322046", "gorgeous": "0.0174896", "fun": "0.00197501", "smart": "0.621552"}, "id": "1628050464142497887_1688403291", "types": "brand", "likes_count": 1293}